LICENSE
MANIFEST.in
README.md
setup.cfg
setup.py
stdeb.cfg
./slapdsock/__about__.py
./slapdsock/__init__.py
./slapdsock/handler.py
./slapdsock/ldaphelper.py
./slapdsock/message.py
./slapdsock/service.py
./slapdsock/test.py
slapdsock.egg-info/PKG-INFO
slapdsock.egg-info/SOURCES.txt
slapdsock.egg-info/dependency_links.txt
slapdsock.egg-info/requires.txt
slapdsock.egg-info/top_level.txt
slapdsock.egg-info/zip-safe